{"code": 0, "data": {"allow_search": false, "attention": 0, "author_title": null, "blocked": false, "can_del": false, "comments": [{"author_title": null, "blocked": false, "can_del": false, "cid": 1753, "name_id": 1, "pid": 1110, "text": "贵性向？", "timestamp": 1639286154}, {"author_title": null, "blocked": false, "can_del": false, "cid": 1757, "name_id": 2, "pid": 1110, "text": "贵性向？", "timestamp": 1639287007}, {"author_title": null, "blocked": false, "can_del": false, "cid": 1764, "name_id": 0, "pid": 1110, "text": "性向均可", "timestamp": 1639288058}], "cw": "性相关", "likenum": 1, "pid": 1110, "poll": null, "reply": 3, "text": "期末压力好大 想被玩 dz男", "timestamp": 1639284824, "type": "text", "url": null}}