{"code": 0, "data": {"allow_search": false, "attention": 0, "author_title": null, "blocked": false, "can_del": false, "comments": [{"author_title": null, "blocked": false, "can_del": false, "cid": 3480, "name_id": 1, "pid": 1721, "text": "平安里那边有很多吉他行 去那里修比较好吧 不要嫌远", "timestamp": 1639467044}, {"author_title": null, "blocked": false, "can_del": false, "cid": 6362, "name_id": 2, "pid": 1721, "text": "test", "timestamp": 1639649109}, {"author_title": null, "blocked": false, "can_del": false, "cid": 6364, "name_id": 2, "pid": 1721, "text": "我是dz，怎么关注列表又没了，我这翻了几百楼来找。心态崩了，以后得把关注的洞号全部记下来了", "timestamp": 1639649162}, {"author_title": null, "blocked": false, "can_del": false, "cid": 6365, "name_id": 2, "pid": 1721, "text": "感谢Alice", "timestamp": 1639649171}], "cw": null, "likenum": 4, "pid": 1721, "poll": null, "reply": 4, "text": "不报太大希望，但还是试一试。\n请问学校周边哪里修吉他比较靠谱，或者避雷也可以", "timestamp": 1639459946, "type": "text", "url": null}}