{"code": 0, "data": {"allow_search": false, "attention": 0, "author_title": null, "blocked": false, "can_del": false, "comments": [{"author_title": null, "blocked": false, "can_del": false, "cid": 5182, "name_id": 1, "pid": 2323, "text": "真的假的，冲塔的都还在", "timestamp": 1639569692}, {"author_title": null, "blocked": false, "can_del": false, "cid": 5184, "name_id": 2, "pid": 2323, "text": "nps是什么？", "timestamp": 1639569950}], "cw": null, "likenum": 1, "pid": 2323, "poll": null, "reply": 2, "text": "新洞会被封禁吗，好像nps的图片被删了", "timestamp": 1639569595, "type": "text", "url": null}}