{"code": 0, "data": {"allow_search": true, "attention": 0, "author_title": null, "blocked": false, "can_del": false, "comments": [{"author_title": null, "blocked": false, "can_del": false, "cid": 8160, "name_id": 1, "pid": 3128, "text": "[tmp]\n杀猪盘", "timestamp": 1639760708}, {"author_title": null, "blocked": false, "can_del": false, "cid": 8174, "name_id": 2, "pid": 3128, "text": "[tmp]\nRe Alice: ？", "timestamp": 1639760972}, {"author_title": null, "blocked": false, "can_del": false, "cid": 8176, "name_id": 3, "pid": 3128, "text": "太丑，吐了", "timestamp": 1639761070}], "cw": "xxg", "likenum": 5, "pid": 3128, "poll": null, "reply": 3, "text": "[tmp]\nhttps://t.me/BJJPB", "timestamp": 1639759187, "type": "text", "url": null}}