{"code": 0, "data": {"allow_search": true, "attention": 0, "author_title": null, "blocked": false, "can_del": false, "comments": [{"author_title": null, "blocked": false, "can_del": false, "cid": 12921, "name_id": 1, "pid": 4507, "text": "[tmp]\n好啊，多多模仿！", "timestamp": 1640085094}, {"author_title": null, "blocked": false, "can_del": false, "cid": 12955, "name_id": 2, "pid": 4507, "text": "人格分裂了？", "timestamp": 1640088013}], "cw": null, "likenum": 3, "pid": 4507, "poll": null, "reply": 2, "text": "[tmp]\n[![TM65X8.jpg](https://s4.ax1x.com/2021/12/21/TM65X8.jpg)](https://imgtu.com/i/TM65X8)\n#见闻录", "timestamp": 1640085029, "type": "text", "url": null}}