{"code": 0, "data": {"allow_search": true, "attention": 0, "author_title": null, "blocked": false, "can_del": false, "comments": [{"author_title": null, "blocked": false, "can_del": false, "cid": 15245, "name_id": 1, "pid": 5182, "text": "艹笑不活了", "timestamp": 1640251738}, {"author_title": null, "blocked": false, "can_del": false, "cid": 15247, "name_id": 2, "pid": 5182, "text": "马都什么？\n\n什么都没啊？\n\n马什么没？", "timestamp": 1640251851}, {"author_title": null, "blocked": false, "can_del": false, "cid": 15255, "name_id": 3, "pid": 5182, "text": "没看懂诶。。。", "timestamp": 1640252483}, {"author_title": null, "blocked": false, "can_del": false, "cid": 15266, "name_id": 4, "pid": 5182, "text": "Re Carol: 我之前以为是藏头诗什么的，结果发现貌似是网民发泄对无法发表事件评论的愤怒，开始答非所问。", "timestamp": 1640253105}, {"author_title": null, "blocked": false, "can_del": false, "cid": 15272, "name_id": 3, "pid": 5182, "text": "Re Dave: 原来是这样", "timestamp": 1640253594}, {"author_title": null, "blocked": false, "can_del": false, "cid": 15426, "name_id": 5, "pid": 5182, "text": "有种恐怖谷的感觉", "timestamp": 1640259399}], "cw": null, "likenum": 9, "pid": 5182, "poll": null, "reply": 6, "text": "新概念树洞\nhttps://www.zhihu.com/question/507795134", "timestamp": 1640251632, "type": "text", "url": null}}