{"code": 0, "data": {"allow_search": true, "attention": false, "author_title": null, "blocked": false, "blocked_count": null, "can_del": false, "comments": [{"author_title": "", "blocked": false, "blocked_count": null, "can_del": false, "cid": 15011, "create_time": 1640240244, "is_blocked": false, "is_tmp": false, "name_id": 1, "text": "tt推荐冈本001，润滑油用玻尿酸人体润滑油", "timestamp": 1640240244}, {"author_title": "", "blocked": false, "blocked_count": null, "can_del": false, "cid": 15127, "create_time": 1640246181, "is_blocked": false, "is_tmp": false, "name_id": 2, "text": "润滑油推荐羞羞哒", "timestamp": 1640246181}, {"author_title": "", "blocked": false, "blocked_count": null, "can_del": false, "cid": 15193, "create_time": 1640248429, "is_blocked": false, "is_tmp": false, "name_id": 3, "text": "冈本001本穷逼可不敢用", "timestamp": 1640248429}, {"author_title": "", "blocked": false, "blocked_count": null, "can_del": false, "cid": 15206, "create_time": 1640249871, "is_blocked": false, "is_tmp": false, "name_id": 3, "text": "润滑液选云泥沙没错哒", "timestamp": 1640249871}, {"author_title": "", "blocked": false, "blocked_count": null, "can_del": false, "cid": 15423, "create_time": 1640259930, "is_blocked": false, "is_tmp": false, "name_id": 4, "text": "不加个延时的么，推荐神油，可以延长时间", "timestamp": 1640259930}], "create_time": 1640239201, "cw": null, "hot_score": null, "is_blocked": false, "is_reported": null, "is_tmp": false, "last_comment_time": 1640239201, "likenum": 1, "n_attentions": 1, "n_comments": 0, "pid": 5130, "poll": {"answers": [{"option": "赞", "votes": 3}, {"option": "踩", "votes": 0}, {"option": "路过", "votes": 0}], "vote": null}, "reply": 0, "text": "#报时 **北京时间 2021-12-23 14:00**\n\n>要么忙着生存要么赶着去死，人总要做点什么\n>　　　　　　　　——《肖申克的救赎》", "timestamp": 1640239201}}