{"code": 0, "data": {"allow_search": false, "attention": 0, "author_title": null, "blocked": false, "can_del": false, "comments": [{"author_title": null, "blocked": false, "can_del": false, "cid": 25153, "name_id": 2, "pid": 9330, "text": "我可以", "timestamp": 1642775209}, {"author_title": null, "blocked": false, "can_del": false, "cid": 25214, "name_id": 2, "pid": 9330, "text": "紫操没人", "timestamp": 1642781887}], "cw": null, "likenum": 0, "pid": 9330, "poll": null, "reply": 2, "text": "晚点有人出来么", "timestamp": 1642769728, "type": "text", "url": null}}