{"code": 0, "data": {"allow_search": true, "attention": false, "author_title": null, "blocked": false, "blocked_count": null, "can_del": false, "comments": [{"author_title": "", "blocked": false, "blocked_count": null, "can_del": false, "cid": 27258, "create_time": 1643517360, "is_blocked": false, "is_tmp": false, "name_id": 1, "text": "可惜不能全选", "timestamp": 1643517360}, {"author_title": "", "blocked": false, "blocked_count": null, "can_del": false, "cid": 27283, "create_time": 1643524723, "is_blocked": false, "is_tmp": true, "name_id": 2, "text": "[tmp]\n该杀！", "timestamp": 1643524723}, {"author_title": "", "blocked": false, "blocked_count": null, "can_del": false, "cid": 27317, "create_time": 1643529947, "is_blocked": false, "is_tmp": true, "name_id": 3, "text": "[tmp]\n该怎么对待协助囚禁维吾尔哈萨克人的所有桃花石人，就该怎么对待他。", "timestamp": 1643529947}, {"author_title": "", "blocked": false, "blocked_count": null, "can_del": false, "cid": 27323, "create_time": 1643530532, "is_blocked": false, "is_tmp": true, "name_id": 2, "text": "[tmp]\nRe Carol: 真 相 与 和 解 委 员 会", "timestamp": 1643530532}, {"author_title": "", "blocked": false, "blocked_count": null, "can_del": false, "cid": 27324, "create_time": 1643530645, "is_blocked": false, "is_tmp": true, "name_id": 2, "text": "[tmp]\n都是邓州人刑平和驻马店人陈全国干的坏事，要报仇去找他们", "timestamp": 1643530645}], "create_time": 1643510198, "cw": "人体艺术", "hot_score": null, "is_blocked": false, "is_reported": null, "is_tmp": false, "last_comment_time": 1643510198, "likenum": 1, "n_attentions": 1, "n_comments": 0, "pid": 10347, "poll": {"answers": [{"option": "美", "votes": 6}, {"option": "不够美", "votes": 0}, {"option": "欣赏不来", "votes": 2}], "vote": null}, "reply": 0, "text": "#人体艺术 [337]\n随手投票，欢迎互动；不定时发，交流审美。\n![]( https://79img.com/i/2021/12/23/3d6oqd.jpg)\nFrom: Bazhenov Denis\n男性，躯体如蓝色湖石上铸造的金铁。\n*往期搜索tag“人体艺术\"查看；更多尺度图片或寻求摄影合作，关注/联系推特 @InsulPhasmid。", "timestamp": 1643510198}}