{"code": 0, "data": {"allow_search": false, "attention": 0, "author_title": null, "blocked": false, "can_del": false, "comments": [{"author_title": null, "blocked": false, "can_del": false, "cid": 31593, "name_id": 1, "pid": 12635, "text": "Re : 离谱", "timestamp": 1645020363}, {"author_title": null, "blocked": false, "can_del": false, "cid": 31632, "name_id": 2, "pid": 12635, "text": "[![H41uBn.jpg](https://s4.ax1x.com/2022/02/17/H41uBn.jpg)](https://imgtu.com/i/H41uBn)", "timestamp": 1645028095}], "cw": null, "likenum": 3, "pid": 12635, "poll": {"answers": [{"option": "是", "votes": 19}, {"option": "不是", "votes": 8}], "vote": null}, "reply": 2, "text": "你是哑巴吗", "timestamp": 1645018882, "type": "text", "url": null}}