{"code": 0, "data": {"allow_search": true, "attention": 0, "author_title": null, "blocked": false, "can_del": false, "comments": [{"author_title": null, "blocked": false, "can_del": false, "cid": 35303, "name_id": 1, "pid": 13979, "text": "[tmp]\n为啥要二极管", "timestamp": 1645780129}, {"author_title": null, "blocked": false, "can_del": false, "cid": 35304, "name_id": 2, "pid": 13979, "text": "党委领导下的校长负责制", "timestamp": 1645780146}, {"author_title": null, "blocked": false, "can_del": false, "cid": 35306, "name_id": 0, "pid": 13979, "text": "Re Alice: 或许应该说 主管？", "timestamp": 1645780224}, {"author_title": null, "blocked": false, "can_del": false, "cid": 35351, "name_id": 3, "pid": 13979, "text": "简而言之党委决策，校长执行", "timestamp": 1645787619}, {"author_title": null, "blocked": false, "can_del": false, "cid": 35464, "name_id": 4, "pid": 13979, "text": "我们都被他们管", "timestamp": 1645799023}, {"author_title": null, "blocked": false, "can_del": false, "cid": 35532, "name_id": 5, "pid": 13979, "text": "校长也是党委副书记", "timestamp": 1645804945}], "cw": null, "likenum": 5, "pid": 13979, "poll": null, "reply": 6, "text": "所以学校到底是党委书记在管还是校长在管", "timestamp": 1645780070, "type": "text", "url": null}}