{"code": 0, "data": {"allow_search": true, "attention": 0, "author_title": null, "blocked": false, "can_del": false, "comments": [{"author_title": null, "blocked": false, "can_del": false, "cid": 37465, "name_id": 1, "pid": 14662, "text": "早睡", "timestamp": 1646096765}, {"author_title": null, "blocked": false, "can_del": false, "cid": 37466, "name_id": 2, "pid": 14662, "text": "把要点名的课放到早课", "timestamp": 1646096783}, {"author_title": null, "blocked": false, "can_del": false, "cid": 37761, "name_id": 3, "pid": 14662, "text": "Re Bob: 确实是这样的", "timestamp": 1646120675}], "cw": null, "likenum": 2, "pid": 14662, "poll": null, "reply": 3, "text": "有什么办法能起来上早课吗", "timestamp": 1646096683, "type": "text", "url": null}}