{"code": 0, "data": {"allow_search": true, "attention": 0, "author_title": null, "blocked": false, "can_del": false, "comments": [{"author_title": null, "blocked": false, "can_del": false, "cid": 43054, "name_id": 1, "pid": 16118, "text": "翻译：劳动者的生命比什么都重要。", "timestamp": 1646554294}], "cw": null, "likenum": 2, "pid": 16118, "poll": {"answers": [{"option": "赞", "votes": 4}, {"option": "踩", "votes": 0}, {"option": "路过", "votes": 0}], "vote": null}, "reply": 1, "text": "#报时 **北京时间 2022-03-06 13:00**\n\n>労働者の命は何よりも大切です。\n>　　　　　　　　——《Internet》", "timestamp": 1646542801, "type": "text", "url": null}}