{"code": 0, "data": {"allow_search": false, "attention": false, "author_title": null, "blocked": false, "blocked_count": null, "can_del": false, "comments": [{"author_title": "", "blocked": false, "blocked_count": null, "can_del": false, "cid": 43140, "create_time": 1646564810, "is_blocked": false, "is_tmp": true, "name_id": 1, "text": "[tmp]\n你给我回来！让我去受苦", "timestamp": 1646564810}, {"author_title": "", "blocked": false, "blocked_count": null, "can_del": false, "cid": 43143, "create_time": 1646565158, "is_blocked": false, "is_tmp": false, "name_id": 2, "text": "dz学习或者生活上遇到了什么困难了吗？", "timestamp": 1646565158}, {"author_title": "", "blocked": false, "blocked_count": null, "can_del": false, "cid": 43157, "create_time": 1646566586, "is_blocked": false, "is_tmp": false, "name_id": 3, "text": "摸摸dz", "timestamp": 1646566586}, {"author_title": "", "blocked": false, "blocked_count": null, "can_del": false, "cid": 43537, "create_time": 1646583502, "is_blocked": false, "is_tmp": false, "name_id": 4, "text": "在美国+1\n不是spring break了吗？好好休息一下吧", "timestamp": 1646583502}, {"author_title": "", "blocked": false, "blocked_count": null, "can_del": false, "cid": 44228, "create_time": 1646658612, "is_blocked": false, "is_tmp": false, "name_id": 5, "text": "拍拍dz", "timestamp": 1646658612}, {"author_title": "", "blocked": false, "blocked_count": null, "can_del": false, "cid": 44245, "create_time": 1646659688, "is_blocked": false, "is_tmp": false, "name_id": 5, "text": "不要难过", "timestamp": 1646659688}], "create_time": 1646564986, "cw": null, "hot_score": null, "is_blocked": false, "is_reported": null, "is_tmp": false, "last_comment_time": 1646564986, "likenum": 1, "n_attentions": 1, "n_comments": 0, "pid": 16193, "poll": null, "reply": 0, "text": "石智丹的党课咋样", "timestamp": 1646564986}}