{"code": 0, "data": {"allow_search": true, "attention": false, "author_title": null, "blocked": false, "blocked_count": null, "can_del": false, "comments": [{"author_title": "", "blocked": false, "blocked_count": null, "can_del": false, "cid": 45024, "create_time": 1646732215, "is_blocked": false, "is_tmp": false, "name_id": 1, "text": "经典反客为主", "timestamp": 1646732215}, {"author_title": "", "blocked": false, "blocked_count": null, "can_del": false, "cid": 45025, "create_time": 1646732239, "is_blocked": false, "is_tmp": false, "name_id": 0, "text": "原谅我爆粗口，不过真被真三傻缺弄得很不爽", "timestamp": 1646732239}, {"author_title": "", "blocked": false, "blocked_count": null, "can_del": false, "cid": 45026, "create_time": 1646732347, "is_blocked": false, "is_tmp": false, "name_id": 0, "text": "Re Alice: 是啊，给恶心到了。换了讲点礼貌的，事先说明一下情况我让个位子也行。问题是这三个就一句不吭夹上来，恶心谁呢？", "timestamp": 1646732347}, {"author_title": "", "blocked": false, "blocked_count": null, "can_del": false, "cid": 45027, "create_time": 1646732443, "is_blocked": false, "is_tmp": false, "name_id": 1, "text": "Re 洞主: qs有够恶心的", "timestamp": 1646732443}, {"author_title": "", "blocked": false, "blocked_count": null, "can_del": false, "cid": 45028, "create_time": 1646732447, "is_blocked": false, "is_tmp": false, "name_id": 0, "text": "一般在食堂吃饭，大家都是尽量和陌生人避开，头一次碰到这种，带兄弟一起变相“逼走”你的", "timestamp": 1646732447}], "create_time": 1646732192, "cw": null, "hot_score": null, "is_blocked": false, "is_reported": null, "is_tmp": false, "last_comment_time": 1646732192, "likenum": 1, "n_attentions": 1, "n_comments": 0, "pid": 16747, "poll": null, "reply": 0, "text": "#14432 所以这5个关注的小伙伴是offer holder吗", "timestamp": 1646732192}}