{"code": 0, "data": {"allow_search": true, "attention": 0, "author_title": null, "blocked": false, "can_del": false, "comments": [{"author_title": null, "blocked": false, "can_del": false, "cid": 45846, "name_id": 1, "pid": 16997, "text": "给个联系方式呗", "timestamp": 1646808288}, {"author_title": null, "blocked": false, "can_del": false, "cid": 45848, "name_id": 0, "pid": 16997, "text": "Re Alice: 清蝻（指我自己", "timestamp": 1646808404}], "cw": null, "likenum": 3, "pid": 16997, "poll": null, "reply": 2, "text": "清蝻发言：我也想谈确定关系就滚床单，半年一年腻了就分开的恋爱。", "timestamp": 1646807931, "type": "text", "url": null}}