{"code": 0, "data": {"allow_search": false, "attention": 0, "author_title": null, "blocked": false, "can_del": false, "comments": [{"author_title": "", "blocked": false, "blocked_count": null, "can_del": false, "cid": 47037, "create_time": 1646921065, "is_blocked": false, "is_tmp": false, "name_id": 1, "text": "生物的本能", "timestamp": 1646921065}, {"author_title": "", "blocked": false, "blocked_count": null, "can_del": false, "cid": 47210, "create_time": 1646927911, "is_blocked": false, "is_tmp": false, "name_id": 2, "text": "为了养老？", "timestamp": 1646927911}], "cw": null, "likenum": 0, "pid": 17407, "poll": null, "reply": 0, "text": "Not Found", "timestamp": 0, "type": "text", "url": null}}