{"code": 0, "data": {"allow_search": true, "attention": 0, "author_title": null, "blocked": false, "can_del": false, "comments": [{"author_title": null, "blocked": false, "can_del": false, "cid": 51415, "name_id": 1, "pid": 18750, "text": "和我试试", "timestamp": 1647337721}, {"author_title": null, "blocked": false, "can_del": false, "cid": 51846, "name_id": 2, "pid": 18750, "text": "啥时候拒绝的", "timestamp": 1647370412}], "cw": null, "likenum": 5, "pid": 18750, "poll": null, "reply": 2, "text": "[tmp]\n后悔把追求者拒绝了，其实应该试试的", "timestamp": 1647337118, "type": "text", "url": null}}