{"code": 0, "data": {"allow_search": true, "attention": 0, "author_title": null, "blocked": false, "can_del": false, "comments": [{"author_title": null, "blocked": false, "can_del": false, "cid": 53781, "name_id": 1, "pid": 19723, "text": "剃须刀", "timestamp": 1647608347}, {"author_title": null, "blocked": false, "can_del": false, "cid": 53782, "name_id": 1, "pid": 19723, "text": "男士香水", "timestamp": 1647608355}, {"author_title": null, "blocked": false, "can_del": false, "cid": 53783, "name_id": 1, "pid": 19723, "text": "领带 腰带", "timestamp": 1647608370}, {"author_title": null, "blocked": false, "can_del": false, "cid": 53786, "name_id": 0, "pid": 19723, "text": "谢谢Alice", "timestamp": 1647608439}], "cw": null, "likenum": 2, "pid": 19723, "poll": null, "reply": 4, "text": "请大家推荐500以内送爸爸的礼物", "timestamp": 1647608281, "type": "text", "url": null}}