{"code": 0, "data": {"allow_search": true, "attention": 0, "author_title": null, "blocked": false, "can_del": false, "comments": [{"author_title": null, "blocked": false, "can_del": false, "cid": 56530, "name_id": 1, "pid": 20783, "text": "要频道还是群？", "timestamp": 1647952915}, {"author_title": null, "blocked": false, "can_del": false, "cid": 56541, "name_id": 2, "pid": 20783, "text": "Re Alice: 我一直分不太清频道和群的差别~", "timestamp": 1647954349}, {"author_title": null, "blocked": false, "can_del": false, "cid": 56607, "name_id": 0, "pid": 20783, "text": "频道吧兄弟，群里全是发约p的", "timestamp": 1647960093}, {"author_title": null, "blocked": false, "can_del": false, "cid": 56608, "name_id": 0, "pid": 20783, "text": "不过我啥都缺", "timestamp": 1647960104}, {"author_title": null, "blocked": false, "can_del": false, "cid": 56609, "name_id": 0, "pid": 20783, "text": "一直不知道上哪找资源，感觉搜索功能啥用没有", "timestamp": 1647960144}], "cw": "#性相关", "likenum": 5, "pid": 20783, "poll": null, "reply": 5, "text": "有无电报分享？", "timestamp": 1647952580, "type": "text", "url": null}}