{"code": -1, "data": {"allow_search": true, "attention": false, "author_title": null, "blocked": false, "blocked_count": null, "can_del": false, "comments": [{"author_title": "", "blocked": false, "blocked_count": null, "can_del": false, "cid": 60726, "create_time": 1648434660, "is_blocked": false, "is_tmp": false, "name_id": 1, "text": "鸡哥bot", "timestamp": 1648434660}, {"author_title": "", "blocked": false, "blocked_count": null, "can_del": false, "cid": 60726, "create_time": "2022-03-28T02:31:00.327733Z", "is_blocked": false, "is_tmp": false, "name_id": 1, "text": "鸡哥bot", "timestamp": 1648434660}], "create_time": "1970-01-01T08:00:00.000000Z", "cw": null, "hot_score": null, "is_blocked": false, "is_reported": null, "is_tmp": false, "last_comment_time": "1970-01-01T08:00:00.000000Z", "likenum": 0, "n_attentions": 0, "n_comments": 0, "pid": 22256, "poll": null, "reply": 0, "text": "内容被删除", "timestamp": 0}}