{"code": 0, "data": {"allow_search": true, "attention": false, "author_title": null, "blocked": false, "blocked_count": null, "can_del": false, "comments": [{"author_title": "", "blocked": false, "blocked_count": null, "can_del": false, "cid": 62179, "create_time": 1648609113, "is_blocked": false, "is_tmp": false, "name_id": 1, "text": "校外附近小区花重金租整租房吧，不过有点贵", "timestamp": 1648609113}, {"author_title": "", "blocked": false, "blocked_count": null, "can_del": false, "cid": 62179, "create_time": "2022-03-30T02:58:33.293511Z", "is_blocked": false, "is_tmp": false, "name_id": 1, "text": "校外附近小区花重金租整租房吧，不过有点贵", "timestamp": 1648609113}, {"author_title": "", "blocked": false, "blocked_count": null, "can_del": false, "cid": 62219, "create_time": 1648613929, "is_blocked": false, "is_tmp": false, "name_id": 2, "text": "穷鬼不配睡眠极度敏感", "timestamp": 1648613929}, {"author_title": "", "blocked": false, "blocked_count": null, "can_del": false, "cid": 62219, "create_time": "2022-03-30T04:18:49.471643Z", "is_blocked": false, "is_tmp": false, "name_id": 2, "text": "穷鬼不配睡眠极度敏感", "timestamp": 1648613929}, {"author_title": "", "blocked": false, "blocked_count": null, "can_del": false, "cid": 65520, "create_time": 1648993121, "is_blocked": false, "is_tmp": false, "name_id": 3, "text": "Re Alice: 主要是家里关注中介几个月了一直没有房源，有的都是平房，不知有什么好渠道赐教？", "timestamp": 1648993121}], "create_time": 1648609327, "cw": null, "hot_score": null, "is_blocked": false, "is_reported": null, "is_tmp": false, "last_comment_time": 1648609327, "likenum": 1, "n_attentions": 1, "n_comments": 0, "pid": 22896, "poll": null, "reply": 0, "text": "![1648609265187.jpeg](https://s2.loli.net/2022/03/30/AB27ZsYKPHUdDQ8.jpg)", "timestamp": 1648609327}}