{"code": 0, "data": {"allow_search": false, "attention": false, "author_title": null, "blocked": false, "blocked_count": null, "can_del": false, "comments": [{"author_title": "", "blocked": false, "blocked_count": null, "can_del": false, "cid": 71526, "create_time": 1649643951, "is_blocked": false, "is_tmp": false, "name_id": 1, "text": "其实，整天把侮辱科学尊重科学放在嘴边的，不是政治家就是智障。", "timestamp": 1649643951}], "create_time": 1649640300, "cw": null, "hot_score": null, "is_blocked": false, "is_reported": null, "is_tmp": false, "last_comment_time": 1649640300, "likenum": 1, "n_attentions": 1, "n_comments": 0, "pid": 26312, "poll": null, "reply": 0, "text": "有的人好像真的以为，上海这么多感染者没有死亡病例是因为政府控制得当、“医疗资源没有发生挤兑”了啊", "timestamp": 1649640300}}