{"code": 0, "data": {"allow_search": true, "attention": false, "author_title": null, "blocked": false, "blocked_count": null, "can_del": false, "comments": [{"author_title": "", "blocked": false, "blocked_count": null, "can_del": false, "cid": 74079, "create_time": 1649865500, "is_blocked": false, "is_tmp": false, "name_id": 1, "text": "共存派又开始擅自代表人民群众了？", "timestamp": 1649865500}, {"author_title": "", "blocked": false, "blocked_count": null, "can_del": false, "cid": 74100, "create_time": 1649866230, "is_blocked": false, "is_tmp": false, "name_id": 2, "text": "得流感也是早晚的事，一个人一辈子得个十几次流感不足为奇，有什么好怕的？", "timestamp": 1649866230}, {"author_title": "", "blocked": false, "blocked_count": null, "can_del": false, "cid": 74111, "create_time": 1649866463, "is_blocked": false, "is_tmp": false, "name_id": 0, "text": "Re Bob: 可是巨婴心理的国民就是多啊，很难接受自己为自己的健康负责。", "timestamp": 1649866463}], "create_time": 1649865292, "cw": null, "hot_score": null, "is_blocked": false, "is_reported": null, "is_tmp": false, "last_comment_time": 1649866463, "likenum": 3, "n_attentions": 3, "n_comments": 3, "pid": 27296, "poll": null, "reply": 3, "text": "清零派又开始吓唬人了？这不是广大人民群众求之不得的吗？\n---\n\n[![LQugJJ.png](https://s1.ax1x.com/2022/04/13/LQugJJ.png)](https://imgtu.com/i/LQugJJ)", "timestamp": 1649865292}}