{"code": 0, "data": {"allow_search": true, "attention": false, "author_title": null, "blocked": false, "blocked_count": null, "can_del": false, "comments": [{"author_title": "", "blocked": false, "blocked_count": null, "can_del": false, "cid": 89890, "create_time": 1651137198, "is_blocked": false, "is_tmp": false, "name_id": 1, "text": "万里归来颜愈少，微笑，笑时犹带岭梅香。", "timestamp": 1651137198}, {"author_title": "", "blocked": false, "blocked_count": null, "can_del": false, "cid": 89891, "create_time": 1651137383, "is_blocked": false, "is_tmp": false, "name_id": 2, "text": "一万年太久 只争朝夕", "timestamp": 1651137383}, {"author_title": "", "blocked": false, "blocked_count": null, "can_del": false, "cid": 89900, "create_time": 1651137780, "is_blocked": false, "is_tmp": false, "name_id": 3, "text": "长风万里送秋雁，对此可以酣高楼。", "timestamp": 1651137780}, {"author_title": "", "blocked": false, "blocked_count": null, "can_del": false, "cid": 89914, "create_time": 1651138291, "is_blocked": false, "is_tmp": false, "name_id": 4, "text": "万里悲秋常作客", "timestamp": 1651138291}, {"author_title": "", "blocked": false, "blocked_count": null, "can_del": false, "cid": 89917, "create_time": 1651138336, "is_blocked": false, "is_tmp": false, "name_id": 5, "text": "四万万人齐下泪 天涯何处是神州", "timestamp": 1651138336}, {"author_title": "", "blocked": false, "blocked_count": null, "can_del": false, "cid": 89919, "create_time": 1651138461, "is_blocked": false, "is_tmp": false, "name_id": 6, "text": "尔来四万八千岁，不与秦塞通人烟", "timestamp": 1651138461}, {"author_title": "", "blocked": false, "blocked_count": null, "can_del": false, "cid": 89922, "create_time": 1651138714, "is_blocked": false, "is_tmp": false, "name_id": 7, "text": "九万里风鹏正举。风休住，蓬舟吹取三山去", "timestamp": 1651138714}, {"author_title": "", "blocked": false, "blocked_count": null, "can_del": false, "cid": 89928, "create_time": 1651139079, "is_blocked": false, "is_tmp": false, "name_id": 8, "text": "万般皆下品，唯有读书高。", "timestamp": 1651139079}, {"author_title": "", "blocked": false, "blocked_count": null, "can_del": false, "cid": 89932, "create_time": 1651139202, "is_blocked": false, "is_tmp": false, "name_id": 8, "text": "九州生气恃风雷，万马齐喑究可哀。", "timestamp": 1651139202}], "create_time": 1651136405, "cw": null, "hot_score": null, "is_blocked": false, "is_reported": null, "is_tmp": false, "last_comment_time": 1651139202, "likenum": 9, "n_attentions": 9, "n_comments": 9, "pid": 32878, "poll": null, "reply": 9, "text": "飞花洞，今日飞花字：万\n试图复刻旧洞？", "timestamp": 1651136405}}