{"code": 0, "data": {"allow_search": true, "attention": false, "author_title": null, "blocked": false, "blocked_count": null, "can_del": false, "comments": [{"author_title": "", "blocked": false, "blocked_count": null, "can_del": false, "cid": 182701, "create_time": 1654213608, "is_blocked": false, "is_tmp": false, "name_id": 1, "text": "我们那落地做核酸就直接走", "timestamp": 1654213608}, {"author_title": "", "blocked": false, "blocked_count": null, "can_del": false, "cid": 182704, "create_time": 1654214640, "is_blocked": false, "is_tmp": false, "name_id": 2, "text": "社区说认可", "timestamp": 1654214640}, {"author_title": "", "blocked": false, "blocked_count": null, "can_del": false, "cid": 182715, "create_time": 1654216557, "is_blocked": false, "is_tmp": false, "name_id": 3, "text": "江蘇国不认", "timestamp": 1654216557}, {"author_title": "", "blocked": false, "blocked_count": null, "can_del": false, "cid": 182745, "create_time": 1654219169, "is_blocked": false, "is_tmp": false, "name_id": 4, "text": "葱省不认", "timestamp": 1654219169}, {"author_title": "", "blocked": false, "blocked_count": null, "can_del": false, "cid": 182797, "create_time": 1654223524, "is_blocked": false, "is_tmp": false, "name_id": 5, "text": "Re Alice: alice是哪里的呜呜呜", "timestamp": 1654223524}], "create_time": 1654209798, "cw": null, "hot_score": null, "is_blocked": false, "is_reported": null, "is_tmp": false, "last_comment_time": 1654223524, "likenum": 6, "n_attentions": 6, "n_comments": 5, "pid": 57603, "poll": null, "reply": 5, "text": "北京大学生返乡的那个政策，认可的省份或市县多吗", "timestamp": 1654209798}}