{"code": 0, "data": {"allow_search": true, "attention": false, "author_title": null, "blocked": false, "blocked_count": null, "can_del": false, "comments": [{"author_title": "", "blocked": false, "blocked_count": null, "can_del": false, "cid": 185608, "create_time": 1654305145, "is_blocked": false, "is_tmp": false, "name_id": 1, "text": "走出社交舒适圈…（你现在不就在干这个233", "timestamp": 1654305145}, {"author_title": "", "blocked": false, "blocked_count": null, "can_del": false, "cid": 185610, "create_time": 1654305246, "is_blocked": false, "is_tmp": false, "name_id": 2, "text": "其实我觉得华子大学很多人脱不了单的原因就是因为男生和女生分布上的隔离了", "timestamp": 1654305246}, {"author_title": "", "blocked": false, "blocked_count": null, "can_del": false, "cid": 185614, "create_time": 1654305550, "is_blocked": false, "is_tmp": false, "name_id": 3, "text": "那么建议和女孩子贴贴（）", "timestamp": 1654305550}, {"author_title": "", "blocked": false, "blocked_count": null, "can_del": false, "cid": 185615, "create_time": 1654305729, "is_blocked": false, "is_tmp": false, "name_id": 4, "text": "性转就是我了...", "timestamp": 1654305729}, {"author_title": "", "blocked": false, "blocked_count": null, "can_del": false, "cid": 185625, "create_time": 1654306323, "is_blocked": false, "is_tmp": false, "name_id": 3, "text": "Re Dave: 那么建议和男孩子贴贴（）", "timestamp": 1654306323}], "create_time": 1654305001, "cw": null, "hot_score": null, "is_blocked": false, "is_reported": null, "is_tmp": false, "last_comment_time": 1654306323, "likenum": 5, "n_attentions": 5, "n_comments": 5, "pid": 58315, "poll": null, "reply": 5, "text": "有点可爱超级害羞偶尔疯癫，热爱生活作息健康，但处在一个几乎全是妹子的环境里，脱单对我来说真的是奢望吧。\n", "timestamp": 1654305001}}