{"code": 0, "data": {"allow_search": true, "attention": false, "author_title": null, "blocked": false, "blocked_count": null, "can_del": false, "comments": [{"author_title": "", "blocked": false, "blocked_count": null, "can_del": false, "cid": 209731, "create_time": 1655035234, "is_blocked": false, "is_tmp": false, "name_id": 1, "text": "草你是考的大雾嘛！", "timestamp": 1655035234}, {"author_title": "", "blocked": false, "blocked_count": null, "can_del": false, "cid": 209770, "create_time": 1655035884, "is_blocked": false, "is_tmp": false, "name_id": 2, "text": "最好不要相信，对你又没好处", "timestamp": 1655035884}, {"author_title": "", "blocked": false, "blocked_count": null, "can_del": false, "cid": 209796, "create_time": 1655036637, "is_blocked": false, "is_tmp": false, "name_id": 3, "text": "要你的名字干嘛呢 毫无必要啊", "timestamp": 1655036637}, {"author_title": "", "blocked": false, "blocked_count": null, "can_del": false, "cid": 209797, "create_time": 1655036661, "is_blocked": false, "is_tmp": false, "name_id": 4, "text": "大物不是周五考吗？", "timestamp": 1655036661}], "create_time": 1655034473, "cw": null, "hot_score": null, "is_blocked": false, "is_reported": null, "is_tmp": false, "last_comment_time": 1655036661, "likenum": 5, "n_attentions": 5, "n_comments": 4, "pid": 63895, "poll": null, "reply": 4, "text": "今天举报了一个作弊的同学 但是监考老师让我留下了自己的名字并说会对我信息保密..我能相信吗 我挺担心以后处处被那个同学针对的orz\n", "timestamp": 1655034473}}