{"code": 0, "data": {"allow_search": false, "attention": false, "author_title": null, "blocked": false, "blocked_count": null, "can_del": false, "comments": [{"author_title": "", "blocked": false, "blocked_count": null, "can_del": false, "cid": 230286, "create_time": 1655524773, "is_blocked": false, "is_tmp": false, "name_id": 2, "text": "狗狗乖", "timestamp": 1655524773}, {"author_title": "", "blocked": false, "blocked_count": null, "can_del": false, "cid": 230287, "create_time": 1655524775, "is_blocked": false, "is_tmp": false, "name_id": 1, "text": "吃我一记打狗棒（狗头）", "timestamp": 1655524775}, {"author_title": "", "blocked": false, "blocked_count": null, "can_del": false, "cid": 230288, "create_time": 1655524828, "is_blocked": false, "is_tmp": false, "name_id": 0, "text": "Re Bob: 狗狗最乖了 只是想要人类的陪伴", "timestamp": 1655524828}, {"author_title": "", "blocked": false, "blocked_count": null, "can_del": false, "cid": 230300, "create_time": 1655525053, "is_blocked": false, "is_tmp": false, "name_id": 3, "text": "狗狗摸摸头", "timestamp": 1655525053}, {"author_title": "", "blocked": false, "blocked_count": null, "can_del": false, "cid": 230309, "create_time": 1655525215, "is_blocked": false, "is_tmp": false, "name_id": 4, "text": "Re 洞主: 那陪你玩玩", "timestamp": 1655525215}, {"author_title": "", "blocked": false, "blocked_count": null, "can_del": false, "cid": 230368, "create_time": 1655526669, "is_blocked": false, "is_tmp": false, "name_id": 5, "text": "汪", "timestamp": 1655526669}], "create_time": 1655524718, "cw": null, "hot_score": null, "is_blocked": false, "is_reported": null, "is_tmp": false, "last_comment_time": 1655526669, "likenum": 6, "n_attentions": 6, "n_comments": 6, "pid": 67673, "poll": null, "reply": 6, "text": "狗狗又无聊了", "timestamp": 1655524718}}