{"code": 0, "data": {"allow_search": false, "attention": false, "author_title": null, "blocked": false, "blocked_count": null, "can_del": false, "comments": [{"author_title": "", "blocked": false, "blocked_count": null, "can_del": false, "cid": 235626, "create_time": 1655651932, "is_blocked": false, "is_tmp": false, "name_id": 1, "text": "一般来讲前50 60应该就能拿到推荐资格了啊", "timestamp": 1655651932}, {"author_title": "", "blocked": false, "blocked_count": null, "can_del": false, "cid": 235628, "create_time": 1655651958, "is_blocked": false, "is_tmp": false, "name_id": 0, "text": "我想想看，上个清本反而将我拉跨了不少，比如学的专业方向，比如绩点排名，比如读研需要的成绩排名等未来深造出路，都阻碍了我不少。", "timestamp": 1655651958}, {"author_title": "", "blocked": false, "blocked_count": null, "can_del": false, "cid": 235629, "create_time": 1655651973, "is_blocked": false, "is_tmp": false, "name_id": 1, "text": "Re Alice: 清北名额要比其他学校多很多的", "timestamp": 1655651973}, {"author_title": "", "blocked": false, "blocked_count": null, "can_del": false, "cid": 235637, "create_time": 1655652027, "is_blocked": false, "is_tmp": false, "name_id": 0, "text": "Re Alice: 工科保不了本校还能去哪啊。去其他学校感觉还不如直接工作", "timestamp": 1655652027}, {"author_title": "", "blocked": false, "blocked_count": null, "can_del": false, "cid": 235638, "create_time": 1655652035, "is_blocked": false, "is_tmp": false, "name_id": 2, "text": "行胜于言，赶紧退学", "timestamp": 1655652035}, {"author_title": "", "blocked": false, "blocked_count": null, "can_del": false, "cid": 235642, "create_time": 1655652073, "is_blocked": false, "is_tmp": false, "name_id": 3, "text": "你可以大四考研", "timestamp": 1655652073}, {"author_title": "", "blocked": false, "blocked_count": null, "can_del": false, "cid": 235643, "create_time": 1655652089, "is_blocked": false, "is_tmp": false, "name_id": 0, "text": "Re Alice: 没觉得。我要是去普通985拿个前几保过来感觉简单不少，真的。从我高中同学就可以看出", "timestamp": 1655652089}, {"author_title": "", "blocked": false, "blocked_count": null, "can_del": false, "cid": 235650, "create_time": 1655652145, "is_blocked": false, "is_tmp": false, "name_id": 0, "text": "Re Alice: 机械，电机，工工有一半是挺多了，其他有的系名额少", "timestamp": 1655652145}, {"author_title": "", "blocked": false, "blocked_count": null, "can_del": false, "cid": 235653, "create_time": 1655652156, "is_blocked": false, "is_tmp": false, "name_id": 1, "text": "Re 洞主: 好老师肯定被校内同学先挑走了啊", "timestamp": 1655652156}, {"author_title": "", "blocked": false, "blocked_count": null, "can_del": false, "cid": 235657, "create_time": 1655652223, "is_blocked": false, "is_tmp": false, "name_id": 4, "text": "我也这样认为，可是能怎么办呢？我打算早点开始考研换专业了，不想保，更保不了研了", "timestamp": 1655652223}, {"author_title": "", "blocked": false, "blocked_count": null, "can_del": false, "cid": 235658, "create_time": 1655652228, "is_blocked": false, "is_tmp": false, "name_id": 0, "text": "Re Carol: 对，但就算考上了我要浪费一年时间去准备。所以我是没觉得考上清华变得有助力感觉更好", "timestamp": 1655652228}, {"author_title": "", "blocked": false, "blocked_count": null, "can_del": false, "cid": 235663, "create_time": 1655652275, "is_blocked": false, "is_tmp": false, "name_id": 0, "text": "Re Alice: 没有的。很多好老师招本校学生都是有名额限制的，一般总会招几个外校的", "timestamp": 1655652275}, {"author_title": "", "blocked": false, "blocked_count": null, "can_del": false, "cid": 235664, "create_time": 1655652277, "is_blocked": false, "is_tmp": false, "name_id": 5, "text": "Re 洞主: 同感", "timestamp": 1655652277}, {"author_title": "", "blocked": false, "blocked_count": null, "can_del": false, "cid": 235666, "create_time": 1655652290, "is_blocked": false, "is_tmp": false, "name_id": 6, "text": "清北本来就是卷王窝，鸡头凤尾的事情。资源本身是严重不足的...还有双非前几那个，假定双非一半摆烂只需要在剩下一半拿到前50%基本能保证满绩，然后双非研究生不行教授给本科生机会说不定还能发文章...再看出国，人家3.9gpa就有最大的逆袭资本了。清北本还是人脉和体制内这两点最重要，但前者一般需要你优秀，后者也不是每一个人都想走这条路", "timestamp": 1655652290}, {"author_title": "", "blocked": false, "blocked_count": null, "can_del": false, "cid": 235669, "create_time": 1655652316, "is_blocked": false, "is_tmp": false, "name_id": 7, "text": "我感觉做金融清华title挺好的", "timestamp": 1655652316}, {"author_title": "", "blocked": false, "blocked_count": null, "can_del": false, "cid": 235677, "create_time": 1655652369, "is_blocked": false, "is_tmp": false, "name_id": 4, "text": "Re Grace: 清华工科也能去做金融吗", "timestamp": 1655652369}, {"author_title": "", "blocked": false, "blocked_count": null, "can_del": false, "cid": 235683, "create_time": 1655652398, "is_blocked": false, "is_tmp": false, "name_id": 7, "text": "Re Dave: 自己找实习 学相关课程 拿出行动力", "timestamp": 1655652398}, {"author_title": "", "blocked": false, "blocked_count": null, "can_del": false, "cid": 235684, "create_time": 1655652400, "is_blocked": false, "is_tmp": false, "name_id": 0, "text": "Re Grace: 金融卷不到保研，没钱出国，本科出来能干啥", "timestamp": 1655652400}, {"author_title": "", "blocked": false, "blocked_count": null, "can_del": false, "cid": 235686, "create_time": 1655652425, "is_blocked": false, "is_tmp": false, "name_id": 0, "text": "Re Grace: 很多金融岗位都要求硕士的", "timestamp": 1655652425}, {"author_title": "", "blocked": false, "blocked_count": null, "can_del": false, "cid": 235687, "create_time": 1655652429, "is_blocked": false, "is_tmp": false, "name_id": 8, "text": "Re : 润出去PHD吧，大清本科比其他学校好使", "timestamp": 1655652429}, {"author_title": "", "blocked": false, "blocked_count": null, "can_del": false, "cid": 235688, "create_time": 1655652434, "is_blocked": false, "is_tmp": false, "name_id": 6, "text": "Re Dave: 你找得到实习就能做，而且工科转金融蛮多的，金融是最看名校的行业，所以也算清北本最大优势之一", "timestamp": 1655652434}, {"author_title": "", "blocked": false, "blocked_count": null, "can_del": false, "cid": 235689, "create_time": 1655652443, "is_blocked": false, "is_tmp": false, "name_id": 9, "text": "清华除了有个牌子其他确实不行", "timestamp": 1655652443}, {"author_title": "", "blocked": false, "blocked_count": null, "can_del": false, "cid": 235692, "create_time": 1655652474, "is_blocked": false, "is_tmp": false, "name_id": 7, "text": "Re 洞主: 这倒是，但第一学历还是很重要的，硕士看得过去就行", "timestamp": 1655652474}, {"author_title": "", "blocked": false, "blocked_count": null, "can_del": false, "cid": 235695, "create_time": 1655652496, "is_blocked": false, "is_tmp": false, "name_id": 0, "text": "Re Francis: 对啊。我也有同学去其他大学本科，绩点比我高不少申请出国的，直接逆袭。", "timestamp": 1655652496}, {"author_title": "", "blocked": false, "blocked_count": null, "can_del": false, "cid": 235705, "create_time": 1655652542, "is_blocked": false, "is_tmp": false, "name_id": 6, "text": "Re Hans: phd只看人脉和科研经历，你清好教授被抢得激烈，本科发出文章的也屈指可数。phd才真是给极优秀的大佬准备的", "timestamp": 1655652542}, {"author_title": "", "blocked": false, "blocked_count": null, "can_del": false, "cid": 235706, "create_time": 1655652575, "is_blocked": false, "is_tmp": false, "name_id": 4, "text": "Re Francis: 说的有道理", "timestamp": 1655652575}, {"author_title": "", "blocked": false, "blocked_count": null, "can_del": false, "cid": 235707, "create_time": 1655652577, "is_blocked": false, "is_tmp": false, "name_id": 0, "text": "Re Francis: 我没同学有钱，没法出国读硕士，绩点又申请国外博士吃亏，国外博士还得异国他乡5年。。。", "timestamp": 1655652577}, {"author_title": "", "blocked": false, "blocked_count": null, "can_del": false, "cid": 235716, "create_time": 1655652634, "is_blocked": false, "is_tmp": false, "name_id": 6, "text": "Re 洞主: 因为清北title在国外院校没那么加分，至少gpa差0.1以上肯定会选gpa高的。而完全不知道到处金银牌大佬的清北竞争有多激烈...", "timestamp": 1655652634}, {"author_title": "", "blocked": false, "blocked_count": null, "can_del": false, "cid": 235720, "create_time": 1655652683, "is_blocked": false, "is_tmp": false, "name_id": 0, "text": "Re Francis: 再激烈也是本校激烈。现在每个实验室真的有招本校名额限制的，一个萝卜一个坑，剩下的留给外校的", "timestamp": 1655652683}, {"author_title": "", "blocked": false, "blocked_count": null, "can_del": false, "cid": 235732, "create_time": 1655652788, "is_blocked": false, "is_tmp": false, "name_id": 0, "text": "Re Francis: 对啊，我外校同学3.9多。外国院校真的看牌子比重有限，主要还是看GPA。甚至有时候申请排名都不用写。", "timestamp": 1655652788}, {"author_title": "", "blocked": false, "blocked_count": null, "can_del": false, "cid": 235733, "create_time": 1655652789, "is_blocked": false, "is_tmp": false, "name_id": 10, "text": "概括一下就是以为高考一考定终生然后发现完全不是这么回事？其实高考也只是分数高的人有优先选择的机会，合适的才是最好的。且不说校外，就校内专业的鄙视链就很明白地表明选择比努力更重要。而且清北也只是保证了不错的下限以及提供冲击更高上限的更充足的机会，至于个体的结局就看个人的选择与努力了。", "timestamp": 1655652789}, {"author_title": "", "blocked": false, "blocked_count": null, "can_del": false, "cid": 235734, "create_time": 1655652799, "is_blocked": false, "is_tmp": false, "name_id": 8, "text": "Re 洞主: 你清车辆工程直博北大力学系是什么水平什么操作？", "timestamp": 1655652799}, {"author_title": "", "blocked": false, "blocked_count": null, "can_del": false, "cid": 235740, "create_time": 1655652885, "is_blocked": false, "is_tmp": false, "name_id": 6, "text": "Re 洞主: 如果高考就打定出国的话不如去南科大上科大或者昆杜这样的，申phd在人脉和资源方面比你清强到哪儿去了....人家以中流985的生源培养出比清北尖子更强的申请水平。当然这是针对普通人的，大佬来清北上限确实是更高。", "timestamp": 1655652885}, {"author_title": "", "blocked": false, "blocked_count": null, "can_del": false, "cid": 235753, "create_time": 1655653006, "is_blocked": false, "is_tmp": false, "name_id": 6, "text": "只能说真的和人生规划强相关，想走计金卷王毕业年薪百万人生巅峰路可以高分来清北卷，想走稳妥保研体制内越老越吃香可以来清北天坑养老，想走出国大佬可以来一般人别来。大概这样", "timestamp": 1655653006}, {"author_title": "", "blocked": false, "blocked_count": null, "can_del": false, "cid": 235760, "create_time": 1655653094, "is_blocked": false, "is_tmp": false, "name_id": 0, "text": "天坑本科养老不了。博士天坑可以养老", "timestamp": 1655653094}, {"author_title": "", "blocked": false, "blocked_count": null, "can_del": false, "cid": 235762, "create_time": 1655653100, "is_blocked": false, "is_tmp": false, "name_id": 11, "text": "完全赞同", "timestamp": 1655653100}, {"author_title": "", "blocked": false, "blocked_count": null, "can_del": false, "cid": 235764, "create_time": 1655653102, "is_blocked": false, "is_tmp": false, "name_id": 6, "text": "已经来了天坑还想自救的可以选一门辅修，然后以比科班更容易拿的gpa+辅修gpa来申科班项目，可能比在科班没卷赢的更有优势。", "timestamp": 1655653102}, {"author_title": "", "blocked": false, "blocked_count": null, "can_del": false, "cid": 235767, "create_time": 1655653133, "is_blocked": false, "is_tmp": false, "name_id": 12, "text": "清北不就是高考分数高吗，除了这点没屁用", "timestamp": 1655653133}, {"author_title": "", "blocked": false, "blocked_count": null, "can_del": false, "cid": 235768, "create_time": 1655653133, "is_blocked": false, "is_tmp": false, "name_id": 0, "text": "Re Francis: 没钱申请科班硕士哇", "timestamp": 1655653133}, {"author_title": "", "blocked": false, "blocked_count": null, "can_del": false, "cid": 235776, "create_time": 1655653240, "is_blocked": false, "is_tmp": false, "name_id": 0, "text": "Re Louis: louis外校的？", "timestamp": 1655653240}, {"author_title": "", "blocked": false, "blocked_count": null, "can_del": false, "cid": 235783, "create_time": 1655653309, "is_blocked": false, "is_tmp": false, "name_id": 6, "text": "Re 洞主: 有魄力可以卖房申请，上了岸一年回本...phd也可以申但5年最宝贵的青春巨大的时间成本，是要和硕士上不了岸的风险相权衡的。穷人本来就没有多少犯错和选择余地。", "timestamp": 1655653309}, {"author_title": "", "blocked": false, "blocked_count": null, "can_del": false, "cid": 235788, "create_time": 1655653363, "is_blocked": false, "is_tmp": false, "name_id": 12, "text": "Re Louis: 走学术只能出国，出国谁认识清华，不过是china mainland罢了；走工业，教学水平一坨屎，只能提供负帮助；唯一的作用就是进体制，可惜现在太多人看明白了，作用缩水了", "timestamp": 1655653363}, {"author_title": "", "blocked": false, "blocked_count": null, "can_del": false, "cid": 235789, "create_time": 1655653379, "is_blocked": false, "is_tmp": false, "name_id": 0, "text": "dz现在意识到了，有钱就是好，直接出国读硕士，规避这个垃圾的境地!!!!!!!!", "timestamp": 1655653379}, {"author_title": "", "blocked": false, "blocked_count": null, "can_del": false, "cid": 235801, "create_time": 1655653477, "is_blocked": false, "is_tmp": false, "name_id": 12, "text": "Re 洞主: 没钱润的🐭🐭", "timestamp": 1655653477}, {"author_title": "", "blocked": false, "blocked_count": null, "can_del": false, "cid": 235806, "create_time": 1655653536, "is_blocked": false, "is_tmp": false, "name_id": 8, "text": "Re 洞主: 重新选择，你们去国内哪所大学？", "timestamp": 1655653536}, {"author_title": "", "blocked": false, "blocked_count": null, "can_del": false, "cid": 235820, "create_time": 1655653709, "is_blocked": false, "is_tmp": false, "name_id": 6, "text": "Re Hans: 去浙大读cs，出国友好", "timestamp": 1655653709}, {"author_title": "", "blocked": false, "blocked_count": null, "can_del": false, "cid": 235827, "create_time": 1655653769, "is_blocked": false, "is_tmp": false, "name_id": 0, "text": "Re Francis: 浙大绩点很友好", "timestamp": 1655653769}, {"author_title": "", "blocked": false, "blocked_count": null, "can_del": false, "cid": 235904, "create_time": 1655654477, "is_blocked": false, "is_tmp": false, "name_id": 6, "text": "忘了说很重要的一点是，在弱一点的985如果能一开始处于前列，那么你的学习动能是强于在清北挣扎的，是一个向上走的趋势。而且会进入大佬圈子，拿到本校顶尖的资源和信息共享。而清北学渣什么都没有，四年一直下坡路。这一上一下实力差距会拉的很大", "timestamp": 1655654477}, {"author_title": "", "blocked": false, "blocked_count": null, "can_del": false, "cid": 235918, "create_time": 1655654637, "is_blocked": false, "is_tmp": false, "name_id": 13, "text": "你系本科就业市场上还挺能打的", "timestamp": 1655654637}, {"author_title": "", "blocked": false, "blocked_count": null, "can_del": false, "cid": 236123, "create_time": 1655656366, "is_blocked": false, "is_tmp": false, "name_id": 14, "text": "同意", "timestamp": 1655656366}, {"author_title": "", "blocked": false, "blocked_count": null, "can_del": false, "cid": 236127, "create_time": 1655656421, "is_blocked": false, "is_tmp": false, "name_id": 15, "text": "Re Francis: 所以天坑倒数怎么自救呀？cz大二下，这学期才能适应和平衡大学学习生活，之前三学期平均下来3.5左右，感觉这学期至少能上3.8，但只剩一年了，是感觉保研还是有点悬QAQ 全年级的均绩应该是3.65这样子，感觉追起来还是有点小难。\ncz还没开始做科研，是不是辜负了清华这么好的一个平台。资源方面cz也不知道啥是好的资源，感觉想学一些其他学科的知识MOOC和coursera等平台都可以找到，最重要的还是兴趣和行动力。\n感觉绩点更多像高考成绩，最重要的功能是保研和出国吧\n", "timestamp": 1655656421}, {"author_title": "", "blocked": false, "blocked_count": null, "can_del": false, "cid": 236510, "create_time": 1655662411, "is_blocked": false, "is_tmp": false, "name_id": 16, "text": "话是这么说，但是为啥你当初选择来清华没去其他985呢", "timestamp": 1655662411}, {"author_title": "", "blocked": false, "blocked_count": null, "can_del": false, "cid": 237233, "create_time": 1655683378, "is_blocked": false, "is_tmp": false, "name_id": 17, "text": "读完研，找工作时还是很看本科的，有的单位本科不行没法进", "timestamp": 1655683378}, {"author_title": "", "blocked": false, "blocked_count": null, "can_del": false, "cid": 237267, "create_time": 1655686860, "is_blocked": false, "is_tmp": false, "name_id": 18, "text": "Re 洞主: 清本目前还是有竞争力的，投递大厂开发岗、研发岗一般不会被卡太多", "timestamp": 1655686860}, {"author_title": "", "blocked": false, "blocked_count": null, "can_del": false, "cid": 237269, "create_time": 1655687056, "is_blocked": false, "is_tmp": false, "name_id": 18, "text": "Re Olivia: 可以考虑去深研院混个硕士，然后转码。。。", "timestamp": 1655687056}, {"author_title": "", "blocked": false, "blocked_count": null, "can_del": false, "cid": 237271, "create_time": 1655687079, "is_blocked": false, "is_tmp": false, "name_id": 19, "text": "自己选的 哭着也要读完 哪来的后悔药 ", "timestamp": 1655687079}, {"author_title": "", "blocked": false, "blocked_count": null, "can_del": false, "cid": 237396, "create_time": 1655691237, "is_blocked": false, "is_tmp": false, "name_id": 20, "text": "你可以转学，清华的分数转学其他学校不是随便选", "timestamp": 1655691237}, {"author_title": "", "blocked": false, "blocked_count": null, "can_del": false, "cid": 237472, "create_time": 1655692739, "is_blocked": false, "is_tmp": false, "name_id": 0, "text": "Re Thomas: 没见过这种操作", "timestamp": 1655692739}, {"author_title": "", "blocked": false, "blocked_count": null, "can_del": false, "cid": 237505, "create_time": 1655693421, "is_blocked": false, "is_tmp": false, "name_id": 21, "text": "去中科院两所", "timestamp": 1655693421}, {"author_title": "", "blocked": false, "blocked_count": null, "can_del": false, "cid": 237594, "create_time": 1655696576, "is_blocked": false, "is_tmp": false, "name_id": 22, "text": "传统工科🐭🐭，准备转码去港新读个msc，在这个学校没卷赢的话确实难顶，放平心态吧", "timestamp": 1655696576}, {"author_title": "", "blocked": false, "blocked_count": null, "can_del": false, "cid": 237624, "create_time": 1655697684, "is_blocked": false, "is_tmp": false, "name_id": 23, "text": "双非前几名很难保研大清吧，目前在现实中没见过。至少我们系，比较🐮的实验室基本还是要清本，不过有一个问题倒是没那么多那么牛的实验室。然后就会发现，清华的研究生教育也这么垃圾，只有碰巧/凭实力选到好导师的人得到了正向增益。", "timestamp": 1655697684}, {"author_title": "", "blocked": false, "blocked_count": null, "can_del": false, "cid": 237734, "create_time": 1655700634, "is_blocked": false, "is_tmp": false, "name_id": 24, "text": "双非保不到清华吧 最低也是前面的211吧 除了一些专业领域非常牛的双非", "timestamp": 1655700634}, {"author_title": "", "blocked": false, "blocked_count": null, "can_del": false, "cid": 237827, "create_time": 1655701636, "is_blocked": false, "is_tmp": false, "name_id": 0, "text": "Re Vivian: 港新多少钱一年哇", "timestamp": 1655701636}, {"author_title": "", "blocked": false, "blocked_count": null, "can_del": false, "cid": 237840, "create_time": 1655701758, "is_blocked": false, "is_tmp": false, "name_id": 25, "text": "感觉这有个预设，就是你去了那些学校后就能搞到顶尖…但事实上哪个学校的顶尖我觉得至少都不比你清人均差", "timestamp": 1655701758}, {"author_title": "", "blocked": false, "blocked_count": null, "can_del": false, "cid": 237856, "create_time": 1655701963, "is_blocked": false, "is_tmp": false, "name_id": 0, "text": "Re Yasmine: 各种普通985一般都有名额  不用C9都 我觉得我可以顶尖的", "timestamp": 1655701963}, {"author_title": "", "blocked": false, "blocked_count": null, "can_del": false, "cid": 237859, "create_time": 1655702002, "is_blocked": false, "is_tmp": false, "name_id": 0, "text": "Re Yasmine: 我高考run去浙大竺可桢现在不香的一批", "timestamp": 1655702002}, {"author_title": "", "blocked": false, "blocked_count": null, "can_del": false, "cid": 237893, "create_time": 1655702399, "is_blocked": false, "is_tmp": false, "name_id": 22, "text": "Re 洞主: 30-40w一年", "timestamp": 1655702399}, {"author_title": "", "blocked": false, "blocked_count": null, "can_del": false, "cid": 238092, "create_time": 1655705752, "is_blocked": false, "is_tmp": false, "name_id": 26, "text": "啊 清本有个幻想就是自己在清华不如意去别的985就能混的很好，而他们不过是高考多错了道选择题", "timestamp": 1655705752}, {"author_title": "", "blocked": false, "blocked_count": null, "can_del": false, "cid": 238189, "create_time": 1655708297, "is_blocked": false, "is_tmp": false, "name_id": 7, "text": "Re Zach: 这也未必…清华大神还是挺多，相同水平不同学校境遇是有差别的…不能说人家是幻想。", "timestamp": 1655708297}, {"author_title": "", "blocked": true, "blocked_count": null, "can_del": false, "cid": 238319, "create_time": 1655711536, "is_blocked": true, "is_tmp": false, "name_id": 27, "text": "", "timestamp": 1655711536}, {"author_title": "", "blocked": false, "blocked_count": null, "can_del": false, "cid": 238398, "create_time": 1655713945, "is_blocked": false, "is_tmp": false, "name_id": 28, "text": "985进清华基本都要专业第一和各种科研竞赛，真的连你清的前百分之八十都比不过吗（理性提问，不和优秀的本科生对比，仅对比保研边缘水平", "timestamp": 1655713945}, {"author_title": "", "blocked": false, "blocked_count": null, "can_del": false, "cid": 238443, "create_time": 1655715594, "is_blocked": false, "is_tmp": false, "name_id": 0, "text": "Re Bob Alice: 我又不是百分之八十。再说了，很多人进了清华沉闷没有正向激励，就算掉到百分之80，换个身心健康的环境就能好起来", "timestamp": 1655715594}, {"author_title": "", "blocked": false, "blocked_count": null, "can_del": false, "cid": 238487, "create_time": 1655717345, "is_blocked": false, "is_tmp": false, "name_id": 23, "text": "Re 洞主: \n说实话，平均资源更少的其他学校更垃圾，环境更沉闷，校园大概率还小，在北京遇到疫情防控全是闹心事儿。\n\n想做前几名就得一直当卷王，每次考试利用各种关系找往年题目，跟各种老师刷脸，小心翼翼地算GPA，甚至为了争保研名额利用/搞翻男女朋友关系，真算不上什么正向激励。\n\n这样苦逼地过了几年之后，好不容易拿到一个保研名额，有的学校千方百计组织学生外推到更好的学校，然后得跟地下工作者似的偷偷搞，本校不敢跟别人说。平时关系好的同学如果成绩相似也会有点心生嫌隙，各自偷偷联系外校老师。\n\n最后八仙过海各显神通之后，可能研究生阶段还遇到了垃圾导师，垃圾实验室，过得依然郁郁不得志。\n\n总之，就是大学之后，完全是个人选择过什么样的生活的问题。尤其是其他学校，考试题目本身区分度并没有那么大，工科的专业课又过于吃往年题目，所以智商有影响，但是影响不大，基本就是要想出头，就得过卷王的生活，其他人享受快乐的大学时光，然后大四考个研。", "timestamp": 1655717345}, {"author_title": "", "blocked": false, "blocked_count": null, "can_del": false, "cid": 238488, "create_time": 1655717373, "is_blocked": false, "is_tmp": false, "name_id": 23, "text": "Re Winnie: *阻止", "timestamp": 1655717373}, {"author_title": "", "blocked": false, "blocked_count": null, "can_del": false, "cid": 238673, "create_time": 1655723206, "is_blocked": false, "is_tmp": false, "name_id": 0, "text": "Re Winnie: 你说的这些清华也都有，一模一样，清华卷王也是这么卷出来的，也考往年题。但是其他学校好卷，比起清华本科来说，是不争的事实", "timestamp": 1655723206}, {"author_title": "", "blocked": false, "blocked_count": null, "can_del": false, "cid": 238674, "create_time": 1655723232, "is_blocked": false, "is_tmp": false, "name_id": 0, "text": "但是其他学校容易卷，比起清华本科来说，是不争的事实", "timestamp": 1655723232}, {"author_title": "", "blocked": false, "blocked_count": null, "can_del": false, "cid": 239205, "create_time": 1655732138, "is_blocked": false, "is_tmp": false, "name_id": 23, "text": "Re 洞主: 对，所以说和性格以及个人选择有关，你去了其他学校未必选择做卷王，做了卷王未必能来清华，来了清华大概率没有好导师可选，哪如直接上清华好(不考虑专业情况下)", "timestamp": 1655732138}, {"author_title": "", "blocked": false, "blocked_count": null, "can_del": false, "cid": 239372, "create_time": 1655734943, "is_blocked": false, "is_tmp": false, "name_id": 28, "text": "Re 洞主:其实洞主就是自己现阶段卷输了不愿意承认，还死抱着曾经的一些辉煌不肯放手，你在这里问，只会得到与你相似的同学的认可\n\n", "timestamp": 1655734943}, {"author_title": "", "blocked": false, "blocked_count": null, "can_del": false, "cid": 239447, "create_time": 1655736289, "is_blocked": false, "is_tmp": false, "name_id": 29, "text": "非清本来说一句，普通985要来清华，基本上只能是第一第二这样子，谁都是拼出来的。我并不觉得985的第一名会比清本的50%容易。so该干嘛干嘛吧，想好要干啥，你的起点已经很高了", "timestamp": 1655736289}, {"author_title": "", "blocked": false, "blocked_count": null, "can_del": false, "cid": 239453, "create_time": 1655736377, "is_blocked": false, "is_tmp": false, "name_id": 29, "text": "Re Carol Alice: 再说一句，其他学校只会更差。普通985只有20左右的保研率，老师一样垃圾，都是自学过来的", "timestamp": 1655736377}, {"author_title": "", "blocked": false, "blocked_count": null, "can_del": false, "cid": 239521, "create_time": 1655737108, "is_blocked": false, "is_tmp": false, "name_id": 0, "text": "Re Carol Alice: 我不觉得清本的50%比985的第一名容易", "timestamp": 1655737108}, {"author_title": "", "blocked": false, "blocked_count": null, "can_del": false, "cid": 239524, "create_time": 1655737137, "is_blocked": false, "is_tmp": false, "name_id": 0, "text": "Re Carol Alice: 这种想法也就是非清本的人自我想想罢了", "timestamp": 1655737137}, {"author_title": "", "blocked": false, "blocked_count": null, "can_del": false, "cid": 239529, "create_time": 1655737188, "is_blocked": false, "is_tmp": false, "name_id": 0, "text": "Re Carol Alice: 清本的50%很大一部分是因为被磨平的自信心。985前几越考越有自信", "timestamp": 1655737188}, {"author_title": "", "blocked": false, "blocked_count": null, "can_del": false, "cid": 239538, "create_time": 1655737310, "is_blocked": false, "is_tmp": false, "name_id": 0, "text": "Re Bob Alice: 呵呵一看就是非清本的同学", "timestamp": 1655737310}, {"author_title": "", "blocked": false, "blocked_count": null, "can_del": false, "cid": 239560, "create_time": 1655737545, "is_blocked": false, "is_tmp": false, "name_id": 0, "text": "Re Carol Alice: 纠正下，你说的985只要第一第二基本是清华计算机系那种。其他很多专业并没有这么严格", "timestamp": 1655737545}, {"author_title": "", "blocked": false, "blocked_count": null, "can_del": false, "cid": 239691, "create_time": 1655738898, "is_blocked": false, "is_tmp": false, "name_id": 29, "text": "Re 洞主: 我npy贵系的，所以我两边都清楚一点，985的第一名真的更难。当然清本的训练量肯定更大一些，这不可否认。dz可以利用在本科的训练去找一份很好的工作了", "timestamp": 1655738898}, {"author_title": "", "blocked": false, "blocked_count": null, "can_del": false, "cid": 240379, "create_time": 1655752124, "is_blocked": false, "is_tmp": false, "name_id": 30, "text": "感觉清华就是，利于出国，如果能保研利于保研清华，其他真的没什么帮助。", "timestamp": 1655752124}, {"author_title": "", "blocked": false, "blocked_count": null, "can_del": false, "cid": 240437, "create_time": 1655772714, "is_blocked": false, "is_tmp": false, "name_id": 31, "text": "中国的大学本科基本都挺差的。要是支持你出国，那么还好。清华本科算是矮子里面挑高个了。看开点，鼠鼠只要在中国，就没什么出路，上不上清华都一样。", "timestamp": 1655772714}, {"author_title": "", "blocked": false, "blocked_count": null, "can_del": false, "cid": 240843, "create_time": 1655784169, "is_blocked": false, "is_tmp": false, "name_id": 32, "text": "Re 洞主: 没必要这么看不起非清本的吧，你不就高考比人家多考了几分，现在在清华卷输了，人家高考少考了几分，大学卷赢了，有什么优劣吗", "timestamp": 1655784169}, {"author_title": "", "blocked": false, "blocked_count": null, "can_del": false, "cid": 240848, "create_time": 1655784232, "is_blocked": false, "is_tmp": false, "name_id": 32, "text": "Re Francis Alice: FA是清本，但是确实不同意dz观点", "timestamp": 1655784232}, {"author_title": "", "blocked": false, "blocked_count": null, "can_del": false, "cid": 240925, "create_time": 1655785400, "is_blocked": false, "is_tmp": false, "name_id": 33, "text": "Re Francis Alice: 复交的同学也没那么热衷你清，dz主要指高考差40分以上的那些中等985...而且清北的分可以高到状元，普通院校没那么大方差，再加上大量的竞赛巨佬，竞争压力不是“少考了几分”可以比的", "timestamp": 1655785400}, {"author_title": "", "blocked": false, "blocked_count": null, "can_del": false, "cid": 241378, "create_time": 1655798043, "is_blocked": false, "is_tmp": false, "name_id": 34, "text": "Re 洞主: 清华的天坑对非清本来说一样很难进，身边的同学基本都是985的国家奖学金，本科也都有一些论文和科研，虽然说不一定比得上洞主，但也不一定是最差的那几个吧，cz本科的时候就有sci一区一作以及挑战杯全国特奖，清本的同学是很优秀，这样贬低别人的努力成果真的很下头", "timestamp": 1655798043}, {"author_title": "", "blocked": false, "blocked_count": null, "can_del": false, "cid": 241892, "create_time": 1655807458, "is_blocked": false, "is_tmp": false, "name_id": 35, "text": "Re 洞主: 有没有一种可能，在中国一个人的发展本来就更和家庭情况高度相关呢。我也曾经像dz这样很多不满，后来也就认了，而且也不能不认。", "timestamp": 1655807458}, {"author_title": "", "blocked": false, "blocked_count": null, "can_del": false, "cid": 242007, "create_time": 1655810867, "is_blocked": false, "is_tmp": false, "name_id": 36, "text": "Re Hans Alice: 有没有一种可能，非清本同学来清本大概率和sci和挑战杯无缘呢了？dz并没有喷非清本或是贬低，而是说清本的资源紧缺辜负了这么多优秀同学的努力", "timestamp": 1655810867}, {"author_title": "", "blocked": false, "blocked_count": null, "can_del": false, "cid": 242131, "create_time": 1655814244, "is_blocked": false, "is_tmp": false, "name_id": 37, "text": "Re Jason Alice: 为啥会觉得清本资源紧缺。。。你要这么说985就不紧缺了？", "timestamp": 1655814244}, {"author_title": "", "blocked": false, "blocked_count": null, "can_del": false, "cid": 242261, "create_time": 1655816629, "is_blocked": false, "is_tmp": false, "name_id": 38, "text": "得看毕业后的目标，否则单纯讨论“好”与否没有意义：对目标是进体制内的人，清北title意义重大，出国资源意义寥寥；对目标是出国的人则反之。从我已经毕业的角度来看，\n对想留国内的人，本科国外>清北=港三>其它985\n对想出国的人，本科国外>港三>清北=其它985", "timestamp": 1655816629}], "create_time": 1655651827, "cw": null, "hot_score": null, "is_blocked": false, "is_reported": null, "is_tmp": false, "last_comment_time": 1655816629, "likenum": 64, "n_attentions": 64, "n_comments": 96, "pid": 68667, "poll": null, "reply": 96, "text": "没有人觉得清北本科很垃圾吗？\n要是进入一个工科，前30%多才能保研，后面的都没有好的去处，如果没钱出国读研就更惨了。\n同时绩点难拿高的，老师教学水平不少很垃圾，部分自学卷王存在导致自己排名又很拉跨。\n保研时候眼睁睁看着自己高考看不起的大学，什么985,211，双非前几都能保进清北，自己当初高考拉跨70-80分才会去的学校的同学保过来，真的很离谱。\n要是去考研，又要浪费一年，清华本科对于很多人来说没有一丝助力，反而增加了未来道路的难度。\n难道是因为本科课教的比其他学校好吗？顶多好一点点，部分老师教学也就那样，但是排名劣势比其他学校更大，未来出路反而比不过其他一般大学。\n只想说，清华本科现在性价比真的很低很低。我真的感受不到任何的一点对我的助力、\n", "timestamp": 1655651827}}