{"code": 0, "data": {"allow_search": true, "attention": false, "author_title": null, "blocked": false, "blocked_count": null, "can_del": false, "comments": [{"author_title": "", "blocked": false, "blocked_count": null, "can_del": false, "cid": 276029, "create_time": 1657019710, "is_blocked": false, "is_tmp": false, "name_id": 1, "text": "高中同学基本满分", "timestamp": 1657019710}, {"author_title": "", "blocked": false, "blocked_count": null, "can_del": false, "cid": 276030, "create_time": 1657019713, "is_blocked": false, "is_tmp": false, "name_id": 2, "text": "你去那些学校也能拿90+", "timestamp": 1657019713}, {"author_title": "", "blocked": false, "blocked_count": null, "can_del": false, "cid": 276031, "create_time": 1657019720, "is_blocked": false, "is_tmp": false, "name_id": 0, "text": "这学期课程有数理方程、基物之类的，同样的课他们为啥能轻松90多，感觉高中也不比他们差，进来以后也一直在认真学", "timestamp": 1657019720}, {"author_title": "", "blocked": false, "blocked_count": null, "can_del": false, "cid": 276034, "create_time": 1657019761, "is_blocked": false, "is_tmp": false, "name_id": 0, "text": "还有随机过程他们甚至能总评98，我真的不理解", "timestamp": 1657019761}, {"author_title": "", "blocked": false, "blocked_count": null, "can_del": false, "cid": 276037, "create_time": 1657019799, "is_blocked": false, "is_tmp": false, "name_id": 1, "text": "不用和他们比", "timestamp": 1657019799}, {"author_title": "", "blocked": false, "blocked_count": null, "can_del": false, "cid": 276042, "create_time": 1657019872, "is_blocked": false, "is_tmp": false, "name_id": 1, "text": "英语可以比比全国性质的四六级", "timestamp": 1657019872}, {"author_title": "", "blocked": false, "blocked_count": null, "can_del": false, "cid": 276050, "create_time": 1657019944, "is_blocked": false, "is_tmp": false, "name_id": 0, "text": "Re Alice: 谢谢Alice 落差有点大 感觉自己被课业压得喘不过气，别人却游刃有余地balance 害，还得调整", "timestamp": 1657019944}, {"author_title": "", "blocked": false, "blocked_count": null, "can_del": false, "cid": 276056, "create_time": 1657020036, "is_blocked": false, "is_tmp": false, "name_id": 3, "text": "因为其他学校的上限是录取最高分，你清的是各路竞赛大佬。同样是前30%拿A难度天上地下", "timestamp": 1657020036}, {"author_title": "", "blocked": false, "blocked_count": null, "can_del": false, "cid": 276069, "create_time": 1657020248, "is_blocked": false, "is_tmp": false, "name_id": 0, "text": "Re Carol: sigh 躺平了 顺利毕业就好了", "timestamp": 1657020248}, {"author_title": "", "blocked": false, "blocked_count": null, "can_del": false, "cid": 276098, "create_time": 1657021176, "is_blocked": false, "is_tmp": false, "name_id": 4, "text": "Re 洞主: 怎么说呢，松神的课其实看你高中基础吧，基物也挺看基础的，这个课4.0-算是主干课里面比较正常的", "timestamp": 1657021176}, {"author_title": "", "blocked": false, "blocked_count": null, "can_del": false, "cid": 276105, "create_time": 1657021286, "is_blocked": false, "is_tmp": false, "name_id": 4, "text": "Re 洞主: 而且我觉得松神的课一定程度上努力是完全完全完全不够的，我们这届有个上海的同学学习极其的努力天天回去手推讲义好几遍，照样考试原始分60左右，物理往后走很大程度上看你对这个科目的感觉和你之前的基础", "timestamp": 1657021286}, {"author_title": "", "blocked": false, "blocked_count": null, "can_del": false, "cid": 276112, "create_time": 1657021480, "is_blocked": false, "is_tmp": false, "name_id": 4, "text": "Re 洞主: 像我们寝室基础比较好期末四个人98+，有的寝室都是高考生平均分70左右，都有", "timestamp": 1657021480}, {"author_title": "", "blocked": false, "blocked_count": null, "can_del": false, "cid": 276130, "create_time": 1657022606, "is_blocked": false, "is_tmp": false, "name_id": 5, "text": "Re Dave: xs，是我们寝室了", "timestamp": 1657022606}, {"author_title": "", "blocked": false, "blocked_count": null, "can_del": false, "cid": 276207, "create_time": 1657025499, "is_blocked": false, "is_tmp": false, "name_id": 0, "text": "Re Dave: 乐，复习一周复变期末没80的我落泪了", "timestamp": 1657025499}], "create_time": 1657019607, "cw": null, "hot_score": null, "is_blocked": false, "is_reported": null, "is_tmp": false, "last_comment_time": 1657025499, "likenum": 8, "n_attentions": 8, "n_comments": 14, "pid": 78149, "poll": null, "reply": 14, "text": "问了一圈高中同学（东南的、南大的），最后课程总评都有90乃至95+，而dz这学期课程全部总评包80+都感觉快失败了，是dz的问题吗", "timestamp": 1657019607}}